{"v":"5.12.2","fr":25.0035705566406,"ip":0,"op":43.9992443005994,"w":48,"h":48,"nm":"Unmute V2","ddd":0,"assets":[],"layers":[{"ddd":0,"ind":1,"ty":4,"nm":"unmutev2-outline-top_s1g1_s2g1_s3g1_s4g2","parent":3,"sr":1,"ks":{"o":{"a":0,"k":100,"ix":11},"r":{"a":0,"k":0,"ix":10},"p":{"a":0,"k":[24,24,0],"ix":2,"l":2},"a":{"a":0,"k":[24,24,0],"ix":1,"l":2},"s":{"a":0,"k":[100,100,100],"ix":6,"l":2}},"ao":0,"shapes":[{"ty":"gr","it":[{"ind":0,"ty":"sh","ix":1,"ks":{"a":0,"k":{"i":[[0,0],[4.619,-4.619]],"o":[[4.619,4.619],[0,0]],"v":[[-2.309,-8.363],[-2.309,8.363]],"c":false},"ix":2},"nm":"Path 1","mn":"ADBE Vector Shape - Group","hd":false},{"ty":"st","c":{"a":0,"k":[0.8470588235294118,0.6627450980392157,0.8588235294117647],"ix":3},"o":{"a":0,"k":100,"ix":4},"w":{"a":0,"k":2.5,"ix":5},"lc":2,"lj":2,"bm":0,"nm":"Stroke 1","mn":"ADBE Vector Graphic - Stroke","hd":false},{"ty":"tr","p":{"a":0,"k":[39.925,23.294],"ix":2},"a":{"a":0,"k":[0,0],"ix":1},"s":{"a":0,"k":[100,100],"ix":3},"r":{"a":0,"k":0,"ix":6},"o":{"a":0,"k":100,"ix":7},"sk":{"a":0,"k":0,"ix":4},"sa":{"a":0,"k":0,"ix":5},"nm":"Transform"}],"nm":"Group 1","np":2,"cix":2,"bm":0,"ix":1,"mn":"ADBE Vector Group","hd":false},{"ty":"gr","it":[{"ind":0,"ty":"sh","ix":1,"ks":{"a":0,"k":{"i":[[0,0],[2.625,-2.624]],"o":[[2.625,2.625],[0,0]],"v":[[-1.312,-4.752],[-1.312,4.752]],"c":false},"ix":2},"nm":"Path 1","mn":"ADBE Vector Shape - Group","hd":false},{"ty":"st","c":{"a":0,"k":[0.8470588235294118,0.6627450980392157,0.8588235294117647],"ix":3},"o":{"a":0,"k":100,"ix":4},"w":{"a":0,"k":2.5,"ix":5},"lc":2,"lj":2,"bm":0,"nm":"Stroke 1","mn":"ADBE Vector Graphic - Stroke","hd":false},{"ty":"tr","p":{"a":0,"k":[35.564,23.294],"ix":2},"a":{"a":0,"k":[0,0],"ix":1},"s":{"a":0,"k":[100,100],"ix":3},"r":{"a":0,"k":0,"ix":6},"o":{"a":0,"k":100,"ix":7},"sk":{"a":0,"k":0,"ix":4},"sa":{"a":0,"k":0,"ix":5},"nm":"Transform"}],"nm":"Group 2","np":2,"cix":2,"bm":0,"ix":2,"mn":"ADBE Vector Group","hd":false}],"ip":0,"op":43.9992443005994,"st":0,"ct":1,"bm":0},{"ddd":0,"ind":2,"ty":4,"nm":"unmutev2-outline-bot_s1g1_s2g2_s3g1_s4g1_background","parent":3,"sr":1,"ks":{"o":{"a":0,"k":100,"ix":11},"r":{"a":0,"k":0,"ix":10},"p":{"a":0,"k":[24,24,0],"ix":2,"l":2},"a":{"a":0,"k":[24,24,0],"ix":1,"l":2},"s":{"a":0,"k":[100,100,100],"ix":6,"l":2}},"ao":0,"shapes":[{"ty":"gr","it":[{"ind":0,"ty":"sh","ix":1,"ks":{"a":0,"k":{"i":[[0,-2.001],[0,0],[1.706,1.046],[0,0],[0.472,0],[0,0],[0,1.414],[0,0],[-1.415,0],[0,0],[-0.403,0.247],[0,0]],"o":[[0,0],[0,2.001],[0,0],[-0.403,-0.247],[0,0],[-1.415,0],[0,0],[0,-1.414],[0,0],[0.472,0],[0,0],[1.706,-1.046]],"v":[[11.654,-8.889],[11.654,8.889],[7.755,11.072],[3.339,8.365],[2.001,7.988],[-9.093,7.988],[-11.654,5.426],[-11.654,-5.426],[-9.093,-7.988],[2.001,-7.988],[3.339,-8.365],[7.755,-11.072]],"c":true},"ix":2},"nm":"Path 1","mn":"ADBE Vector Shape - Group","hd":false},{"ty":"st","c":{"a":0,"k":[0.8470588235294118,0.6627450980392157,0.8588235294117647],"ix":3},"o":{"a":0,"k":100,"ix":4},"w":{"a":0,"k":2.5,"ix":5},"lc":2,"lj":2,"bm":0,"nm":"Stroke 1","mn":"ADBE Vector Graphic - Stroke","hd":false},{"ty":"fl","c":{"a":0,"k":[1,1,1],"ix":4},"o":{"a":0,"k":100,"ix":5},"r":1,"bm":0,"nm":"Fill 1","mn":"ADBE Vector Graphic - Fill","hd":false},{"ty":"tr","p":{"a":0,"k":[18.531,21.991],"ix":2},"a":{"a":0,"k":[0,0],"ix":1},"s":{"a":0,"k":[100,100],"ix":3},"r":{"a":0,"k":0,"ix":6},"o":{"a":0,"k":100,"ix":7},"sk":{"a":0,"k":0,"ix":4},"sa":{"a":0,"k":0,"ix":5},"nm":"Transform"}],"nm":"Group 3","np":3,"cix":2,"bm":0,"ix":1,"mn":"ADBE Vector Group","hd":false}],"ip":0,"op":43.9992443005994,"st":0,"ct":1,"bm":0},{"ddd":0,"ind":3,"ty":4,"nm":"unmutev2-outline-bot_s1g1_s2g1_s3g1_s4g1_background","sr":1,"ks":{"o":{"a":0,"k":100,"ix":11},"r":{"a":1,"k":[{"i":{"x":[0.833],"y":[0.833]},"o":{"x":[0.167],"y":[0.167]},"t":0,"s":[0]},{"i":{"x":[0.833],"y":[0.833]},"o":{"x":[0.167],"y":[0.167]},"t":16.667,"s":[-12]},{"i":{"x":[0.833],"y":[0.833]},"o":{"x":[0.167],"y":[0.167]},"t":27.778,"s":[0]},{"t":39.9993130005449,"s":[0]}],"ix":10,"x":"var $bm_rt;\nvar n, n, t, t, v, amp, freq, decay;\n$bm_rt = n = 0;\nif (numKeys > 0) {\n    $bm_rt = n = nearestKey(time).index;\n    if (key(n).time > time) {\n        n--;\n    }\n}\nif (n == 0) {\n    $bm_rt = t = 0;\n} else {\n    $bm_rt = t = $bm_sub(time, key(n).time);\n}\nif (n > 0 && t < 1) {\n    v = velocityAtTime($bm_sub(key(n).time, $bm_div(thisComp.frameDuration, 10)));\n    amp = 0.05;\n    freq = 2;\n    decay = 9;\n    $bm_rt = $bm_sum(value, $bm_div($bm_mul($bm_mul(v, amp), Math.sin($bm_mul($bm_mul($bm_mul(freq, t), 2), Math.PI))), Math.exp($bm_mul(decay, t))));\n} else {\n    $bm_rt = value;\n}"},"p":{"a":1,"k":[{"i":{"x":0.833,"y":0.833},"o":{"x":0.167,"y":0.167},"t":0,"s":[6.125,21.75,0],"to":[-0.354,0.167,0],"ti":[-0.188,0,0]},{"i":{"x":0.833,"y":0.833},"o":{"x":0.167,"y":0.167},"t":16.667,"s":[4,22.75,0],"to":[0.188,0,0],"ti":[-0.354,0.167,0]},{"i":{"x":0.833,"y":0.833},"o":{"x":0.167,"y":0.167},"t":27.778,"s":[7.25,21.75,0],"to":[0.191,-0.09,0],"ti":[0.336,-0.026,0]},{"i":{"x":0.833,"y":0.833},"o":{"x":0.167,"y":0.167},"t":33.332,"s":[6.442,21.693,0],"to":[-0.118,0.009,0],"ti":[0.036,-0.01,0]},{"i":{"x":0.833,"y":0.833},"o":{"x":0.167,"y":0.167},"t":36.666,"s":[6.854,21.723,0],"to":[-0.051,0.015,0],"ti":[0.051,0,0]},{"t":39.9993130005449,"s":[6.125,21.75,0]}],"ix":2,"l":2,"x":"var $bm_rt;\nvar n, n, t, t, v, amp, freq, decay;\n$bm_rt = n = 0;\nif (numKeys > 0) {\n    $bm_rt = n = nearestKey(time).index;\n    if (key(n).time > time) {\n        n--;\n    }\n}\nif (n == 0) {\n    $bm_rt = t = 0;\n} else {\n    $bm_rt = t = $bm_sub(time, key(n).time);\n}\nif (n > 0 && t < 1) {\n    v = velocityAtTime($bm_sub(key(n).time, $bm_div(thisComp.frameDuration, 10)));\n    amp = 0.05;\n    freq = 2;\n    decay = 9;\n    $bm_rt = $bm_sum(value, $bm_div($bm_mul($bm_mul(v, amp), Math.sin($bm_mul($bm_mul($bm_mul(freq, t), 2), Math.PI))), Math.exp($bm_mul(decay, t))));\n} else {\n    $bm_rt = value;\n}"},"a":{"a":0,"k":[6.125,21.75,0],"ix":1,"l":2},"s":{"a":1,"k":[{"i":{"x":[0.833,0.833,0.833],"y":[0.833,0.833,0.833]},"o":{"x":[0.167,0.167,0.167],"y":[0.167,0.167,0.167]},"t":0,"s":[100,100,100]},{"i":{"x":[0.833,0.833,0.833],"y":[0.833,0.833,0.833]},"o":{"x":[0.167,0.167,0.167],"y":[0.167,0.167,0.167]},"t":16.667,"s":[87,100,100]},{"i":{"x":[0.833,0.833,0.833],"y":[0.833,0.833,0.833]},"o":{"x":[0.167,0.167,0.167],"y":[0.167,0.167,0.167]},"t":27.778,"s":[106,100,100]},{"i":{"x":[0.833,0.833,0.833],"y":[0.833,0.833,0.833]},"o":{"x":[0.167,0.167,0.167],"y":[0.167,0.167,0.167]},"t":33.332,"s":[97,100,100]},{"i":{"x":[0.833,0.833,0.833],"y":[0.833,0.833,0.833]},"o":{"x":[0.167,0.167,0.167],"y":[0.167,0.167,0.167]},"t":36.666,"s":[101,100,100]},{"t":39.9993130005449,"s":[100,100,100]}],"ix":6,"l":2,"x":"var $bm_rt;\nvar n, n, t, t, v, amp, freq, decay;\n$bm_rt = n = 0;\nif (numKeys > 0) {\n    $bm_rt = n = nearestKey(time).index;\n    if (key(n).time > time) {\n        n--;\n    }\n}\nif (n == 0) {\n    $bm_rt = t = 0;\n} else {\n    $bm_rt = t = $bm_sub(time, key(n).time);\n}\nif (n > 0 && t < 1) {\n    v = velocityAtTime($bm_sub(key(n).time, $bm_div(thisComp.frameDuration, 10)));\n    amp = 0.05;\n    freq = 2;\n    decay = 9;\n    $bm_rt = $bm_sum(value, $bm_div($bm_mul($bm_mul(v, amp), Math.sin($bm_mul($bm_mul($bm_mul(freq, t), 2), Math.PI))), Math.exp($bm_mul(decay, t))));\n} else {\n    $bm_rt = value;\n}"}},"ao":0,"shapes":[{"ty":"gr","it":[{"ind":0,"ty":"sh","ix":1,"ks":{"a":0,"k":{"i":[[1.404,0],[0,0],[0,1.403],[0,0],[0,0],[0,0]],"o":[[0,0],[-1.404,0],[0,0],[0,0],[0,0],[0,1.403]],"v":[[0,3.268],[0,3.268],[-2.541,0.727],[-2.541,-3.268],[2.541,-3.268],[2.541,0.727]],"c":true},"ix":2},"nm":"Path 1","mn":"ADBE Vector Shape - Group","hd":false},{"ty":"st","c":{"a":0,"k":[0.8470588235294118,0.6627450980392157,0.8588235294117647],"ix":3},"o":{"a":0,"k":100,"ix":4},"w":{"a":0,"k":2.5,"ix":5},"lc":2,"lj":2,"bm":0,"nm":"Stroke 1","mn":"ADBE Vector Graphic - Stroke","hd":false},{"ty":"fl","c":{"a":0,"k":[1,1,1],"ix":4},"o":{"a":0,"k":100,"ix":5},"r":1,"bm":0,"nm":"Fill 1","mn":"ADBE Vector Graphic - Fill","hd":false},{"ty":"tr","p":{"a":0,"k":[13.92,33.245],"ix":2},"a":{"a":0,"k":[0,0],"ix":1},"s":{"a":0,"k":[100,100],"ix":3},"r":{"a":0,"k":0,"ix":6},"o":{"a":0,"k":100,"ix":7},"sk":{"a":0,"k":0,"ix":4},"sa":{"a":0,"k":0,"ix":5},"nm":"Transform"}],"nm":"Group 4","np":3,"cix":2,"bm":0,"ix":1,"mn":"ADBE Vector Group","hd":false}],"ip":0,"op":43.9992443005994,"st":0,"ct":1,"bm":0}],"markers":[],"props":{}}